collective.lineage-3.0.0-py3.11-nspkg.pth
collective/lineage/__init__.py
collective/lineage/adapters.py
collective/lineage/browser.py
collective/lineage/configure.zcml
collective/lineage/descriptors.py
collective/lineage/events.py
collective/lineage/interfaces.py
collective/lineage/switcher.pt
collective/lineage/testing.py
collective/lineage/upgrades.py
collective/lineage/utils.py
collective/lineage/locales/collective.lineage.pot
collective/lineage/locales/rebuild_i18n.sh
collective/lineage/locales/de/LC_MESSAGES/collective.lineage.po
collective/lineage/locales/es/LC_MESSAGES/collective.lineage.po
collective/lineage/locales/it/LC_MESSAGES/collective.lineage.po
collective/lineage/locales/nl/LC_MESSAGES/collective.lineage.po
collective/lineage/locales/pt_BR/LC_MESSAGES/collective.lineage.po
collective/lineage/locales/zh_CN/LC_MESSAGES/collective.lineage.po
collective/lineage/profiles/default/actions.xml
collective/lineage/profiles/default/browserlayer.xml
collective/lineage/profiles/default/metadata.xml
collective/lineage/profiles/default/viewlets.xml
collective/lineage/profiles/uninstall/actions.xml
collective/lineage/profiles/uninstall/browserlayer.xml
collective/lineage/tests/__init__.py
collective/lineage/tests/test_adapter.py
collective/lineage/tests/test_browser.py
collective/lineage/tests/test_setup.py
collective/lineage/tests/test_utils.py
collective.lineage-3.0.0.dist-info/METADATA
collective.lineage-3.0.0.dist-info/WHEEL
collective.lineage-3.0.0.dist-info/entry_points.txt
collective.lineage-3.0.0.dist-info/namespace_packages.txt
collective.lineage-3.0.0.dist-info/top_level.txt
collective.lineage-3.0.0.dist-info/RECORD
