Metadata-Version: 2.1
Name: collective.lineage
Version: 3.0.0
Summary: The microsite creation product for Plone
Home-page: https://pypi.org/project/collective-lineage
Author: Six Feet Up, Inc.
Author-email: info@sixfeetup.com
License: GPL
Keywords: plone lineage
Classifier: Development Status :: 5 - Production/Stable
Classifier: Environment :: Web Environment
Classifier: Framework :: Plone
Classifier: Framework :: Plone :: 5.2
Classifier: Framework :: Plone :: 6.0
Classifier: Framework :: Plone :: Addon
Classifier: Intended Audience :: End Users/Desktop
Classifier: Intended Audience :: System Administrators
Classifier: License :: OSI Approved :: GNU General Public License (GPL)
Classifier: Operating System :: OS Independent
Classifier: Programming Language :: Python
Classifier: Programming Language :: Python :: 3.8
Classifier: Programming Language :: Python :: 3.9
Classifier: Programming Language :: Python :: 3.10
Classifier: Programming Language :: Python :: 3.11
Classifier: Topic :: Software Development :: Libraries :: Python Modules
Requires-Python: >=3.8
Requires-Dist: setuptools
Requires-Dist: Products.CMFCore
Requires-Dist: Products.CMFPlone
Requires-Dist: five.localsitemanager
Requires-Dist: plone.browserlayer
Requires-Dist: plone.dexterity
Requires-Dist: plone.folder
Provides-Extra: test
Requires-Dist: plone.app.testing ; extra == 'test'
Requires-Dist: plone.testing >=5.0.0 ; extra == 'test'
